fuzzy_delta_time/__init__.py
fuzzy_delta_time/cli.py
fuzzy_delta_time/fuzzy_delta_time.py
fuzzy_delta_time-0.0.4.dist-info/AUTHORS.rst
fuzzy_delta_time-0.0.4.dist-info/LICENSE
fuzzy_delta_time-0.0.4.dist-info/METADATA
fuzzy_delta_time-0.0.4.dist-info/WHEEL
fuzzy_delta_time-0.0.4.dist-info/entry_points.txt
fuzzy_delta_time-0.0.4.dist-info/top_level.txt
fuzzy_delta_time-0.0.4.dist-info/RECORD
