Metadata-Version: 2.1
Name: fuzzy-delta-time
Version: 0.0.4
Summary: Python library to compute a fuzzy time difference.
Home-page: https://github.com/hXtreme/fuzzy_delta_time
Author: Harsh Parekh
Author-email: h.x.dev@outlook.com
License: GNU General Public License v3
Keywords: fuzzy_delta_time
Platform: UNKNOWN
Classifier: Development Status :: 2 - Pre-Alpha
Classifier: Intended Audience :: Developers
Classifier: License :: OSI Approved :: GNU General Public License v3 (GPLv3)
Classifier: Natural Language :: English
Classifier: Programming Language :: Python :: 3
Classifier: Programming Language :: Python :: 3.6
Classifier: Programming Language :: Python :: 3.7
Classifier: Programming Language :: Python :: 3.8
Requires-Python: >=3.6
Requires-Dist: Click (>=7.1.2)
